Andreani_QA_Functions/Functions.py
Andreani_QA_Functions/__init__.py
Andreani_QA_Functions-0.0.48.dist-info/METADATA
Andreani_QA_Functions-0.0.48.dist-info/WHEEL
Andreani_QA_Functions-0.0.48.dist-info/top_level.txt
Andreani_QA_Functions-0.0.48.dist-info/RECORD
