Metadata-Version: 2.1
Name: Andreani-QA-Functions
Version: 0.0.48
Summary: Functions para ejecución de casos automatizados
Home-page: UNKNOWN
Author: AndreaniTesting
Author-email: user_appglatest@andreani.com
License: MIT
Platform: UNKNOWN
Requires-Dist: cx-Oracle
Requires-Dist: pymsteams
Requires-Dist: pyodbc
Requires-Dist: openpyxl
Requires-Dist: pymongo
Requires-Dist: shareplum
Requires-Dist: cryptography
Requires-Dist: Andreani-QA-Sikuli
